setup.py
jsonserver/__init__.py
jsonserver/core.py
jsonserver/exceptions.py
jsonserver/main.py
jsonserver/routes.py
jsonserver/storage.py
jsonserver.egg-info/PKG-INFO
jsonserver.egg-info/SOURCES.txt
jsonserver.egg-info/dependency_links.txt
jsonserver.egg-info/entry_points.txt
jsonserver.egg-info/top_level.txt