Metadata-Version: 1.1
Name: jsonserver
Version: 0.1.0
Summary: Simple pythonic json backend server to easily test frontends
Home-page: http://github.com/timofurrer/jsonserver
Author: Timo Furrer
Author-email: tuxtimo@gmail.com
License: GPL
Download-URL: http://github.com/timofurrer/jsonserver
Platform: Linux
Platform: Windows
Platform: MAC OS X
Classifier: Development Status :: 4 - Beta
Classifier: Environment :: Console
Classifier: Intended Audience :: Developers
Classifier: Intended Audience :: Education
Classifier: Intended Audience :: Other Audience
Classifier: License :: OSI Approved :: GNU General Public License v3 (GPLv3)
Classifier: Natural Language :: English
Classifier: Operating System :: OS Independent
Classifier: Programming Language :: Python
Classifier: Programming Language :: Python :: 3
Classifier: Programming Language :: Python :: 3.2
Classifier: Programming Language :: Python :: 3.4
Classifier: Programming Language :: Python :: Implementation
Classifier: Topic :: Education :: Testing
Classifier: Topic :: Software Development
Classifier: Topic :: Software Development :: Testing
